data_product_sdk/__init__.py
data_product_sdk/aws/__init__.py
data_product_sdk/aws/dynamodb.py
data_product_sdk/aws/glue_databrew.py
data_product_sdk/aws/s3.py
data_product_sdk/aws/secrets_manager.py
data_product_sdk/aws/sqs.py
data_product_sdk/cortex_airflow/__init__.py
data_product_sdk/cortex_airflow/data_platform/__init__.py
data_product_sdk/cortex_airflow/data_platform/operators/__init__.py
data_product_sdk/cortex_airflow/data_platform/operators/databrew_operators.py
data_product_sdk/cortex_airflow/data_platform/operators/diego_operators.py
data_product_sdk/cortex_airflow/data_platform/operators/diego_operators_databricks.py
data_product_sdk/cortex_airflow/data_platform/operators/sid_operators.py
data_product_sdk/cortex_airflow/data_platform/sensors/__init__.py
data_product_sdk/cortex_airflow/data_platform/sensors/diego_sensors.py
data_product_sdk/cortex_airflow/data_platform/sensors/sid_sensors.py
data_product_sdk/cortex_airflow/data_platform/task_groups/__init__.py
data_product_sdk/cortex_airflow/data_platform/task_groups/diego_groups.py
data_product_sdk/cortex_airflow/data_platform/task_groups/emr_groups.py
data_product_sdk/cortex_airflow/data_platform/task_groups/sid_groups.py
data_product_sdk/cortex_airflow/data_platform/utils/__init__.py
data_product_sdk/cortex_airflow/data_platform/utils/airflow_utils.py
data_product_sdk/cortex_airflow/data_platform/utils/aws_utils.py
data_product_sdk/cortex_airflow/data_platform/utils/file_utils.py
data_product_sdk/cortex_airflow/data_platform/utils/http_utils.py
data_product_sdk/cortex_airflow/data_platform/utils/sid_utils.py
data_product_sdk/cortex_airflow/data_platform/utils/slack_utils.py
data_product_sdk/cortex_airflow/data_platform/utils/time_utils.py
data_product_sdk/cortex_databricks/__init__.py
data_product_sdk/cortex_databricks/data_platform/aws_utils.py
data_product_sdk/cortex_databricks/data_platform/databricks_utils.py
data_product_sdk/cortex_databricks/data_platform/kafka_utils.py
cortex_data_product_sdk-0.3.124.dist-info/LICENSE
cortex_data_product_sdk-0.3.124.dist-info/METADATA
cortex_data_product_sdk-0.3.124.dist-info/WHEEL
cortex_data_product_sdk-0.3.124.dist-info/top_level.txt
cortex_data_product_sdk-0.3.124.dist-info/RECORD
