Metadata-Version: 2.1
Name: cortex-data-product-sdk
Version: 0.3.124
Summary: Cortex Data Product SDK
Classifier: Programming Language :: Python :: 3
Classifier: License :: OSI Approved :: MIT License
Classifier: Operating System :: OS Independent
License-File: LICENSE
Requires-Dist: awswrangler <=2.17.0,>=2.11.0
Requires-Dist: pyarrow <=10.0.0,>=4.0.1
Requires-Dist: python-version <3.10
Requires-Dist: kafka-python ==2.0.2
